pytest_message/__init__.py
pytest_message/notifier.py
pytest_message/plugin.py
pytest_message/listeners/__init__.py
pytest_message/listeners/listiner.py
pytest_message/listeners/slack_listener.py
pytest_message-1.0.0.dist-info/LICENSE
pytest_message-1.0.0.dist-info/METADATA
pytest_message-1.0.0.dist-info/WHEEL
pytest_message-1.0.0.dist-info/entry_points.txt
pytest_message-1.0.0.dist-info/top_level.txt
pytest_message-1.0.0.dist-info/RECORD
