Metadata-Version: 2.1
Name: pytest-message
Version: 1.0.0
Summary: Pytest plugin for sending report message of marked tests execution
Home-page: https://github.com/VStoilovskyi/pytest-message
License: Apache 2.0
Keywords: notify,pytest,message
Classifier: Framework :: Pytest
Classifier: Programming Language :: Python :: 3.8
Classifier: Programming Language :: Python :: 3.9
License-File: LICENSE
Requires-Dist: pytest (>=6.2.5)
Requires-Dist: slack-sdk (>=3.11.2)
